gostep/__init__.py
gostep/aggregator.py
gostep/builders.py
gostep/cmd_validator.py
gostep/consts.py
gostep/file_manager.py
gostep/gcloud_ops.py
gostep/repo_service.py
gostep-0.1.0b17.data/scripts/gostep
gostep-0.1.0b17.dist-info/LICENSE.txt
gostep-0.1.0b17.dist-info/METADATA
gostep-0.1.0b17.dist-info/WHEEL
gostep-0.1.0b17.dist-info/top_level.txt
gostep-0.1.0b17.dist-info/RECORD
