Metadata-Version: 2.1
Name: gostep
Version: 0.1.0b17
Summary: Serverless Templates Provider for Google Cloud platform
Home-page: https://github.com/gostep-cli/gostep
Author: Lahiru Pathirage
Author-email: lpsandaruwan@gmail.com
License: MIT
Platform: UNKNOWN
License-File: LICENSE.txt
Requires-Dist: google-api-python-client
Requires-Dist: google-auth-httplib2
Requires-Dist: google-auth-oauthlib
Requires-Dist: google-cloud-storage
Requires-Dist: oauth2client
Requires-Dist: pyyaml
Requires-Dist: svn
